api/__init__.py
api/login.py
api/profile.py
api/register.py
api/user.py
api/viewsets.py
migrations/0001_initial.py
migrations/0002_userprofile_last_updated.py
migrations/0003_changehistory_userprofile_changes.py
migrations/0004_remove_changehistory_user_changehistory_owner.py
migrations/0005_alter_userprofile_changes.py
migrations/0006_chat_created_chat_messages_message_created.py
migrations/0007_message_uuid.py
migrations/0008_message_read.py
migrations/0009_user_automated.py
migrations/0010_remove_message_chat_remove_message_recipient_and_more.py
migrations/0011_remove_consumerconnections_connections_and_more.py
migrations/0012_userprofile_contact_secret.py
migrations/0013_userprofile_is_bot.py
migrations/0014_userprofile_description_and_more.py
migrations/0015_userprofile_reveal_secret.py
migrations/__init__.py
models/__init__.py
models/history.py
models/profile.py
models/settings.py
models/user.py
oc_core_django-1.0.0.dist-info/METADATA
oc_core_django-1.0.0.dist-info/WHEEL
oc_core_django-1.0.0.dist-info/top_level.txt
oc_core_django-1.0.0.dist-info/RECORD
